nextpy/__init__.py
nextpy/__init__.pyi
nextpy/__main__.py
nextpy/ai/__init__.py
nextpy/ai/agent/__init__.py
nextpy/ai/agent/agentbox/Readme.md
nextpy/ai/agent/agentbox/__init__.py
nextpy/ai/agent/agentbox/_utils.py
nextpy/ai/agent/agentbox/agentbox.py
nextpy/ai/agent/agentbox/basebox.py
nextpy/ai/agent/agentbox/tinybox.py
nextpy/ai/agent/base_agent.py
nextpy/ai/agent/chat.py
nextpy/ai/agent/completion.py
nextpy/ai/config.py
nextpy/ai/config.🤖
nextpy/ai/engine/__init__.py
nextpy/ai/engine/_grammar.py
nextpy/ai/engine/_program.py
nextpy/ai/engine/_program_executor.py
nextpy/ai/engine/_utils.py
nextpy/ai/engine/_variable_stack.py
nextpy/ai/engine/library/__init__.py
nextpy/ai/engine/library/_add.py
nextpy/ai/engine/library/_assistant.py
nextpy/ai/engine/library/_await.py
nextpy/ai/engine/library/_block.py
nextpy/ai/engine/library/_break.py
nextpy/ai/engine/library/_callable.py
nextpy/ai/engine/library/_contains.py
nextpy/ai/engine/library/_context.py
nextpy/ai/engine/library/_each.py
nextpy/ai/engine/library/_equal.py
nextpy/ai/engine/library/_example.py
nextpy/ai/engine/library/_function.py
nextpy/ai/engine/library/_gen.py
nextpy/ai/engine/library/_geneach.py
nextpy/ai/engine/library/_greater.py
nextpy/ai/engine/library/_if.py
nextpy/ai/engine/library/_input.py
nextpy/ai/engine/library/_len.py
nextpy/ai/engine/library/_less.py
nextpy/ai/engine/library/_multiply.py
nextpy/ai/engine/library/_not.py
nextpy/ai/engine/library/_notequal.py
nextpy/ai/engine/library/_output.py
nextpy/ai/engine/library/_parse.py
nextpy/ai/engine/library/_range.py
nextpy/ai/engine/library/_role.py
nextpy/ai/engine/library/_select.py
nextpy/ai/engine/library/_set.py
nextpy/ai/engine/library/_shell.py
nextpy/ai/engine/library/_strip.py
nextpy/ai/engine/library/_subtract.py
nextpy/ai/engine/library/_system.py
nextpy/ai/engine/library/_unless.py
nextpy/ai/engine/library/_user.py
nextpy/ai/engine/llms/__init__.py
nextpy/ai/engine/llms/_deep_speed.py
nextpy/ai/engine/llms/_llm.py
nextpy-0.3.3.dist-info/LICENSE
nextpy-0.3.3.dist-info/METADATA
nextpy-0.3.3.dist-info/WHEEL
nextpy-0.3.3.dist-info/entry_points.txt
nextpy-0.3.3.dist-info/RECORD
