Metadata-Version: 2.1
Name: nextpy
Version: 0.3.3
Summary: ⚡The Pure Python Framework for Web Apps, Meticulously Optimized for 🤖AI agents🤖. World's first AMS🥇
Home-page: https://nextpy.org
License: Apache-2.0
Keywords: web,framework
Author: Team dotagent
Author-email: anurag@dotagent.ai
Requires-Python: >=3.8,<4.0
Classifier: Development Status :: 4 - Beta
Classifier: License :: OSI Approved :: Apache Software License
Classifier: Programming Language :: Python :: 3
Classifier: Programming Language :: Python :: 3.8
Classifier: Programming Language :: Python :: 3.9
Classifier: Programming Language :: Python :: 3.10
Classifier: Programming Language :: Python :: 3.11
Requires-Dist: alembic (>=1.11.1,<2.0.0)
Requires-Dist: charset-normalizer (>=3.3.2,<4.0.0)
Requires-Dist: cloudpickle (>=2.2.1,<3.0.0)
Requires-Dist: distro (>=1.8.0,<2.0.0) ; sys_platform == "linux"
Requires-Dist: fastapi (>=0.96.0,<0.97.0)
Requires-Dist: gunicorn (>=20.1.0,<21.0.0)
Requires-Dist: httpx (>=0.24.0,<0.26.0)
Requires-Dist: jinja2 (>=3.1.2,<4.0.0)
Requires-Dist: packaging (>=23.1,<24.0)
Requires-Dist: pipdeptree (>=2.13.0,<3.0.0)
Requires-Dist: platformdirs (>=3.10.0,<4.0.0)
Requires-Dist: psutil (>=5.9.4,<6.0.0)
Requires-Dist: pydantic (>=1.10.2,<2.0.0)
Requires-Dist: pyjokes (>=0.6.0,<0.7.0)
Requires-Dist: pylint (>=3.0.3,<4.0.0)
Requires-Dist: python-engineio (!=4.6.0)
Requires-Dist: python-multipart (>=0.0.5,<0.0.6)
Requires-Dist: python-socketio (>=5.7.0,<6.0.0)
Requires-Dist: redis (>=4.3.5,<5.0.0)
Requires-Dist: rich (>=13.0.0,<14.0.0)
Requires-Dist: sqlmodel (>=0.0.14,<0.0.15)
Requires-Dist: starlette-admin (>=0.9.0,<0.10.0)
Requires-Dist: tabulate (>=0.9.0,<0.10.0)
Requires-Dist: typer (>=0.4.2,<1)
Requires-Dist: uvicorn (>=0.20.0,<0.21.0) ; python_version < "3.12"
Requires-Dist: uvicorn (>=0.24.0,<0.25.0) ; python_version >= "3.12"
Requires-Dist: watchdog (>=2.3.1,<3.0.0)
Requires-Dist: watchfiles (>=0.19.0,<0.20.0)
Requires-Dist: websockets (>=10.4)
Requires-Dist: wrapt (>=1.11.0,<2.0.0) ; python_version < "3.11"
Requires-Dist: wrapt (>=1.14.0,<2.0.0) ; python_version >= "3.11"
Project-URL: Documentation, https://docs.nextpy.org/getting-started/introduction
Project-URL: Repository, https://github.com/dot-agent/nextpy
